.coveragerc
.testr.conf
AUTHORS
ChangeLog
README.md
README.rst
babel.cfg
bindep.txt
requirements.txt
setup.cfg
setup.py
test-requirements.txt
tox.ini
gaiaclient/__init__.py
gaiaclient/_i18n.py
gaiaclient/client.py
gaiaclient/exc.py
gaiaclient/shell.py
gaiaclient/common/__init__.py
gaiaclient/common/base.py
gaiaclient/common/exceptions.py
gaiaclient/common/http.py
gaiaclient/common/https.py
gaiaclient/common/progressbar.py
gaiaclient/common/utils.py
gaiaclient/tests/__init__.py
gaiaclient/tests/utils.py
gaiaclient/tests/functional/README.rst
gaiaclient/tests/functional/__init__.py
gaiaclient/tests/functional/base.py
gaiaclient/tests/functional/test_readonly_glance.py
gaiaclient/tests/functional/hooks/post_test_hook.sh
gaiaclient/tests/unit/__init__.py
gaiaclient/tests/unit/fixture_data.py
gaiaclient/tests/unit/test_base.py
gaiaclient/tests/unit/test_client.py
gaiaclient/tests/unit/test_exc.py
gaiaclient/tests/unit/test_http.py
gaiaclient/tests/unit/test_progressbar.py
gaiaclient/tests/unit/test_shell.py
gaiaclient/tests/unit/test_ssl.py
gaiaclient/tests/unit/test_utils.py
gaiaclient/tests/unit/v1/__init__.py
gaiaclient/tests/unit/v1/test_dcs.py
gaiaclient/tests/unit/v1/test_dcs_shell.py
gaiaclient/tests/unit/v1/test_flavors.py
gaiaclient/tests/unit/v1/test_flavors_shell.py
gaiaclient/tests/unit/v1/test_images.py
gaiaclient/tests/unit/v1/test_images_shell.py
gaiaclient/tests/unit/v1/test_networks.py
gaiaclient/tests/unit/v1/test_networks_shell.py
gaiaclient/tests/unit/v1/test_servers.py
gaiaclient/tests/unit/v1/test_servers_shell.py
gaiaclient/tests/unit/v1/test_usages.py
gaiaclient/tests/unit/v1/test_usages_shell.py
gaiaclient/tests/unit/v1/test_versions.py
gaiaclient/tests/unit/v1/test_versions_shell.py
gaiaclient/tests/unit/v1/test_volumes.py
gaiaclient/tests/unit/v1/test_volumes_shell.py
gaiaclient/tests/unit/var/badcert.crt
gaiaclient/tests/unit/var/ca.crt
gaiaclient/tests/unit/var/certificate.crt
gaiaclient/tests/unit/var/expired-cert.crt
python_gaiaclient.egg-info/PKG-INFO
python_gaiaclient.egg-info/SOURCES.txt
python_gaiaclient.egg-info/dependency_links.txt
python_gaiaclient.egg-info/entry_points.txt
python_gaiaclient.egg-info/not-zip-safe
python_gaiaclient.egg-info/pbr.json
python_gaiaclient.egg-info/requires.txt
python_gaiaclient.egg-info/top_level.txt
