Metadata-Version: 1.1
Name: python-gaiaclient
Version: 1.0.1
Summary: Client library for Zeus Gaia API
Home-page: UNKNOWN
Author: Zeus
Author-email: zeus-dev@zte.com.cn
License: Apache License, Version 2.0
Platform: UNKNOWN
Classifier: Development Status :: 1 - Planning
Classifier: Environment :: Console
Classifier: Environment :: OpenStack
Classifier: Intended Audience :: Developers
Classifier: Intended Audience :: Information Technology
Classifier: License :: OSI Approved :: Apache Software License
Classifier: Operating System :: OS Independent
Classifier: Programming Language :: Python
Classifier: Programming Language :: Python :: 2
Classifier: Programming Language :: Python :: 2.7
